lftools/__init__.py
lftools/config.py
lftools/conftest.py
lftools/deploy.py
lftools/github_helper.py
lftools/helpers.py
lftools/ldap_cli.py
lftools/lfidapi.py
lftools/license.py
lftools/oauth2_helper.py
lftools/schema.py
lftools/api/__init__.py
lftools/api/client.py
lftools/api/exceptions.py
lftools/api/endpoints/__init__.py
lftools/api/endpoints/gerrit.py
lftools/api/endpoints/nexus2.py
lftools/api/endpoints/nexus3.py
lftools/api/endpoints/readthedocs.py
lftools/cli/__init__.py
lftools/cli/config.py
lftools/cli/dco.py
lftools/cli/deploy.py
lftools/cli/gerrit.py
lftools/cli/github_cli.py
lftools/cli/infofile.py
lftools/cli/ldap_cli.py
lftools/cli/lfidapi.py
lftools/cli/license.py
lftools/cli/nexus.py
lftools/cli/no_cmd.py
lftools/cli/rtd.py
lftools/cli/schema.py
lftools/cli/sign.py
lftools/cli/utils.py
lftools/cli/version.py
lftools/cli/jenkins/__init__.py
lftools/cli/jenkins/builds.py
lftools/cli/jenkins/jobs.py
lftools/cli/jenkins/nodes.py
lftools/cli/jenkins/plugins.py
lftools/cli/jenkins/token.py
lftools/cli/nexus2/__init__.py
lftools/cli/nexus2/privilege.py
lftools/cli/nexus2/repository.py
lftools/cli/nexus2/role.py
lftools/cli/nexus2/user.py
lftools/cli/nexus3/__init__.py
lftools/cli/nexus3/asset.py
lftools/cli/nexus3/privilege.py
lftools/cli/nexus3/repository.py
lftools/cli/nexus3/role.py
lftools/cli/nexus3/script.py
lftools/cli/nexus3/tag.py
lftools/cli/nexus3/task.py
lftools/cli/nexus3/user.py
lftools/git/__init__.py
lftools/git/gerrit.py
lftools/git/templates/config-params.yaml
lftools/git/templates/gitreview
lftools/git/templates/project.yaml
lftools/git/templates/serverCredentialMappings.yaml
lftools/jenkins/__init__.py
lftools/jenkins/token.py
lftools/nexus/__init__.py
lftools/nexus/cmd.py
lftools/nexus/release_docker_hub.py
lftools/nexus/util.py
lftools/openstack/__init__.py
lftools/openstack/cluster.py
lftools/openstack/cmd.py
lftools/openstack/image.py
lftools/openstack/no_cmd.py
lftools/openstack/object.py
lftools/openstack/server.py
lftools-0.37.21.dist-info/METADATA
lftools-0.37.21.dist-info/WHEEL
lftools-0.37.21.dist-info/entry_points.txt
lftools-0.37.21.dist-info/top_level.txt
lftools-0.37.21.dist-info/RECORD
