Metadata-Version: 2.4
Name: lftools
Version: 0.37.21
Summary: Linux Foundation Release Engineering Tools
Author-email: LF Release Engineering <releng@linuxfoundation.org>
Maintainer-email: LF Release Engineering <releng@linuxfoundation.org>
License: EPL-1.0
Project-URL: Homepage, https://docs.releng.linuxfoundation.org/projects/lftools
Project-URL: Bug Tracker, https://github.com/lfit/releng-tools/issues
Project-URL: Documentation, https://docs.releng.linuxfoundation.org/projects/lftools
Project-URL: Source Code, https://github.com/lfit/releng-lftools
Platform: linux
Classifier: Intended Audience :: Developers
Classifier: Intended Audience :: Information Technology
Classifier: Operating System :: POSIX :: Linux
Classifier: Programming Language :: Python
Classifier: Programming Language :: Python :: 3.8
Classifier: Programming Language :: Python :: 3.9
Classifier: Programming Language :: Python :: 3.10
Classifier: Programming Language :: Python :: 3.11
Classifier: Programming Language :: Python :: 3.12
Classifier: Programming Language :: Python :: 3.13
Requires-Python: <3.14,>=3.8
Requires-Dist: appdirs
Requires-Dist: aspy.yaml
Requires-Dist: attrs
Requires-Dist: beautifulsoup4
Requires-Dist: boto3
Requires-Dist: bs4
Requires-Dist: certifi
Requires-Dist: cfgv
Requires-Dist: chardet
Requires-Dist: click
Requires-Dist: defusedxml
Requires-Dist: Deprecated
Requires-Dist: dnspython
Requires-Dist: docker
Requires-Dist: email-validator
Requires-Dist: filelock
Requires-Dist: GitPython
Requires-Dist: httplib2<0.31.0
Requires-Dist: identify
Requires-Dist: idna
Requires-Dist: jinja2
Requires-Dist: jsonschema
Requires-Dist: lxml
Requires-Dist: multi-key-dict
Requires-Dist: munch
Requires-Dist: nodeenv
Requires-Dist: oauth2client
Requires-Dist: openstacksdk>=2.1.0
Requires-Dist: pbr
Requires-Dist: pyasn1
Requires-Dist: pyasn1-modules
Requires-Dist: pygerrit2
Requires-Dist: PyGithub
Requires-Dist: PyJWT
Requires-Dist: pyrsistent
Requires-Dist: python-jenkins
Requires-Dist: PyYAML
Requires-Dist: requests>=2.32.0
Requires-Dist: rsa
Requires-Dist: ruamel.yaml
Requires-Dist: ruamel.yaml.clib
Requires-Dist: six
Requires-Dist: soupsieve
Requires-Dist: tabulate
Requires-Dist: toml
Requires-Dist: tqdm
Requires-Dist: urllib3<3.0.0,>=1.26.15
Requires-Dist: websocket-client
Requires-Dist: wrapt
Requires-Dist: xdg
Provides-Extra: dev
Requires-Dist: mypy; extra == "dev"
Provides-Extra: docs
Requires-Dist: lfdocs-conf; extra == "docs"
Requires-Dist: reno; extra == "docs"
Requires-Dist: sphinxcontrib-programoutput; extra == "docs"
Provides-Extra: ldap
Requires-Dist: python-ldap~=3.1.0; extra == "ldap"
Provides-Extra: openstack
Requires-Dist: osc-lib~=2.2.0; extra == "openstack"
Provides-Extra: test
Requires-Dist: pytest==8.3.5; extra == "test"
Requires-Dist: pytest-click==1.1.0; extra == "test"
Requires-Dist: pytest-cov==5.0.0; extra == "test"
Requires-Dist: pytest-datafiles==3.0.0; extra == "test"
Requires-Dist: pytest-mock==3.14.0; extra == "test"
Requires-Dist: pytest-responses==0.5.1; extra == "test"
